strato_query/__init__.py
strato_query/aggregations.py
strato_query/api_query.py
strato_query/authentication.py
strato_query/constants.py
strato_query/exceptions.py
strato_query/filters.py
strato_query/query_structures.py
strato_query-3.10.2.dist-info/LICENSE
strato_query-3.10.2.dist-info/METADATA
strato_query-3.10.2.dist-info/WHEEL
strato_query-3.10.2.dist-info/top_level.txt
strato_query-3.10.2.dist-info/RECORD
