Metadata-Version: 2.1
Name: strato-query
Version: 3.10.2
Summary: StratoDem Analytics API tools
Home-page: https://github.com/StratoDem/strato-query
Author: Michael Clawar, Raaid Arshad, Eric Linden
Author-email: tech@stratodem.com
License: MIT
License-File: LICENSE
